hkfdb/Database.py
hkfdb/__init__.py
hkfdb-2.3.dist-info/LICENSE
hkfdb-2.3.dist-info/METADATA
hkfdb-2.3.dist-info/WHEEL
hkfdb-2.3.dist-info/top_level.txt
hkfdb-2.3.dist-info/RECORD
