Metadata-Version: 2.1
Name: hkfdb
Version: 2.3
Summary: Hong Kong Finance Database.
Home-page: https://www.hkfdb.net
Author: Hong Kong Finance Database Team
Author-email: info@hkfdb.net
Classifier: Programming Language :: Python :: 3
Classifier: License :: OSI Approved :: MIT License
Classifier: Operating System :: OS Independent
License-File: LICENSE
Requires-Dist: pandas
Requires-Dist: requests
Requires-Dist: beautifulsoup4
Requires-Dist: pymongo
